setup.py
iyiyiy/__init__.py
iyiyiy/cFunction.py
iyiyiy.egg-info/PKG-INFO
iyiyiy.egg-info/SOURCES.txt
iyiyiy.egg-info/dependency_links.txt
iyiyiy.egg-info/requires.txt
iyiyiy.egg-info/top_level.txt