Metadata-Version: 2.1
Name: iyiyiy
Version: 0.0.1
Summary: Min
Home-page: http://github.com/iyyoo9806/iyiyiy
Author: Yooinyoung
Author-email: iyyoo980615@naver.com
License: MIT
Keywords: calendar,isoweek,listsum
